Workbook

Sheet COMPARATIVO ANUAL
A1: COMPARATIVO ANUAL — 2025 vs 2026 | Bela Cereais Grupo
A2: Indicador | B2: 2025 | C2: 2026 | D2: Variação (R$) | E2: Variação (%)
A3: Lucro Bruto (Contratos) | B3: =SUMIF(BD_LUCRO!B2:B202,2025,BD_LUCRO!K2:K202) -> 6965952.7 | C3: =SUMIF(BD_LUCRO!B2:B202,2026,BD_LUCRO!K2:K202) -> 1775078.2 | D3: =C3-B3 -> -5190874.4 | E3: =IF(B3<>0,(C3-B3)/ABS(B3),0) -> -0.74517797
A4: (-) Total Frete | B4: =-SUMIF(BD_LUCRO!B2:B202,2025,BD_LUCRO!L2:L202) -> -3259171.8 | C4: =-SUMIF(BD_LUCRO!B2:B202,2026,BD_LUCRO!L2:L202) -> -158677 | D4: =C4-B4 -> 3100494.8 | E4: =IF(B4<>0,(C4-B4)/ABS(B4),0) -> 0.9513137
A5: (-) Impostos sobre contratos | B5: =-SUMIF(BD_LUCRO!B2:B202,2025,BD_LUCRO!M2:M202) -> -7281.97 | C5: =-SUMIF(BD_LUCRO!B2:B202,2026,BD_LUCRO!M2:M202) -> -60833.59 | D5: =C5-B5 -> -53551.62 | E5: =IF(B5<>0,(C5-B5)/ABS(B5),0) -> -7.3540017
A6: (-) Comissões | B6: =-SUMIF(BD_LUCRO!B2:B202,2025,BD_LUCRO!N2:N202) -> -1826139.8 | C6: =-SUMIF(BD_LUCRO!B2:B202,2026,BD_LUCRO!N2:N202) -> -154927.64 | D6: =C6-B6 -> 1671212.2 | E6: =IF(B6<>0,(C6-B6)/ABS(B6),0) -> 0.91516113
A7: (=) Lucro Líquido Operacional | B7: =SUMIF(BD_LUCRO!B2:B202,2025,BD_LUCRO!O2:O202) -> 4200075.4 | C7: =SUMIF(BD_LUCRO!B2:B202,2026,BD_LUCRO!O2:O202) -> 1275125.2 | D7: =C7-B7 -> -2924950.3 | E7: =IF(B7<>0,(C7-B7)/ABS(B7),0) -> -0.69640423
A8: (-) Despesas Administrativas | B8: =-SUMIF(BD_DESP!B2:B663,2025,BD_DESP!E2:E663) -> -3677506.7 | C8: =-SUMIF(BD_DESP!B2:B663,2026,BD_DESP!E2:E663) -> -726854.62 | D8: =C8-B8 -> 2950652.1 | E8: =IF(B8<>0,(C8-B8)/ABS(B8),0) -> 0.80235125
A9: (=) LUCRO LÍQUIDO FINAL | B9: =B7+B8 -> 522568.7 | C9: =C7+C8 -> 548270.53 | D9: =C9-B9 -> 25701.83 | E9: =IF(B9<>0,(C9-B9)/ABS(B9),0) -> 0.049183638
A11: Peso Total (Kg) | B11: =SUMIF(BD_LUCRO!B2:B202,2025,BD_LUCRO!I2:I202) -> 25716499 | C11: =SUMIF(BD_LUCRO!B2:B202,2026,BD_LUCRO!I2:I202) -> 8652682 | D11: =C11-B11 -> -17063817 | E11: =IF(B11<>0,(C11-B11)/ABS(B11),0) -> -0.66353577
A12: Nº Contratos | B12: =COUNTIF(BD_LUCRO!B2:B202,2025) -> 124 | C12: =COUNTIF(BD_LUCRO!B2:B202,2026) -> 77 | D12: =C12-B12 -> -47 | E12: =IF(B12<>0,(C12-B12)/ABS(B12),0) -> -0.37903226
A13: Margem Bruta % | B13: =IF(B3<>0,(B3+B4+B5+B6)/B3,0) -> 0.26893078 | C13: =IF(C3<>0,(C3+C4+C5+C6)/C3,0) -> 0.78905818 | D13: =C13-B13 -> 0.5201274 | E13: =IF(B13<>0,(C13-B13)/ABS(B13),0) -> 1.9340568
A14: Margem Líquida % | B14: =IF(B3<>0,B9/B3,0) -> 0.07501755 | C14: =IF(C3<>0,C9/C3,0) -> 0.30887119 | D14: =C14-B14 -> 0.23385364 | E14: =IF(B14<>0,(C14-B14)/ABS(B14),0) -> 3.1173191
A16: EVOLUÇÃO MENSAL COMPARATIVA — Lucro Líquido Operacional
A17: Mês | B17: 2025 | C17: 2026 | D17: Δ R$ | E17: Δ %
A18: Janeiro | B18: =SUMPRODUCT((BD_LUCRO!B2:B202=2025)*(MONTH(BD_LUCRO!C2:C202)=1)*IF(ISNUMBER(BD_LUCRO!O2:O202),BD_LUCRO!O2:O202,0)) -> 106231.7 | C18: =SUMPRODUCT((BD_LUCRO!B2:B202=2026)*(MONTH(BD_LUCRO!C2:C202)=1)*IF(ISNUMBER(BD_LUCRO!O2:O202),BD_LUCRO!O2:O202,0)) -> 259819.54 | D18: =C18-B18 -> 153587.84 | E18: =IF(B18<>0,(C18-B18)/ABS(B18),0) -> 1.4457816
A19: Fevereiro | B19: =SUMPRODUCT((BD_LUCRO!B2:B202=2025)*(MONTH(BD_LUCRO!C2:C202)=2)*IF(ISNUMBER(BD_LUCRO!O2:O202),BD_LUCRO!O2:O202,0)) -> 716883.4 | C19: =SUMPRODUCT((BD_LUCRO!B2:B202=2026)*(MONTH(BD_LUCRO!C2:C202)=2)*IF(ISNUMBER(BD_LUCRO!O2:O202),BD_LUCRO!O2:O202,0)) -> 566766.6 | D19: =C19-B19 -> -150116.8 | E19: =IF(B19<>0,(C19-B19)/ABS(B19),0) -> -0.20940198
A20: Março | B20: =SUMPRODUCT((BD_LUCRO!B2:B202=2025)*(MONTH(BD_LUCRO!C2:C202)=3)*IF(ISNUMBER(BD_LUCRO!O2:O202),BD_LUCRO!O2:O202,0)) -> 1154496.8 | C20: =SUMPRODUCT((BD_LUCRO!B2:B202=2026)*(MONTH(BD_LUCRO!C2:C202)=3)*IF(ISNUMBER(BD_LUCRO!O2:O202),BD_LUCRO!O2:O202,0)) -> 448539.01 | D20: =C20-B20 -> -705957.83 | E20: =IF(B20<>0,(C20-B20)/ABS(B20),0) -> -0.61148529
A21: Abril | B21: =SUMPRODUCT((BD_LUCRO!B2:B202=2025)*(MONTH(BD_LUCRO!C2:C202)=4)*IF(ISNUMBER(BD_LUCRO!O2:O202),BD_LUCRO!O2:O202,0)) -> 499270.09 | C21: =SUMPRODUCT((BD_LUCRO!B2:B202=2026)*(MONTH(BD_LUCRO!C2:C202)=4)*IF(ISNUMBER(BD_LUCRO!O2:O202),BD_LUCRO!O2:O202,0)) -> 0 | D21: =C21-B21 -> -499270.09 | E21: =IF(B21<>0,(C21-B21)/ABS(B21),0) -> -1
A22: Maio | B22: =SUMPRODUCT((BD_LUCRO!B2:B202=2025)*(MONTH(BD_LUCRO!C2:C202)=5)*IF(ISNUMBER(BD_LUCRO!O2:O202),BD_LUCRO!O2:O202,0)) -> 520095.42 | C22: =SUMPRODUCT((BD_LUCRO!B2:B202=2026)*(MONTH(BD_LUCRO!C2:C202)=5)*IF(ISNUMBER(BD_LUCRO!O2:O202),BD_LUCRO!O2:O202,0)) -> 0 | D22: =C22-B22 -> -520095.42 | E22: =IF(B22<>0,(C22-B22)/ABS(B22),0) -> -1
A23: Junho | B23: =SUMPRODUCT((BD_LUCRO!B2:B202=2025)*(MONTH(BD_LUCRO!C2:C202)=6)*IF(ISNUMBER(BD_LUCRO!O2:O202),BD_LUCRO!O2:O202,0)) -> 60153.78 | C23: =SUMPRODUCT((BD_LUCRO!B2:B202=2026)*(MONTH(BD_LUCRO!C2:C202)=6)*IF(ISNUMBER(BD_LUCRO!O2:O202),BD_LUCRO!O2:O202,0)) -> 0 | D23: =C23-B23 -> -60153.78 | E23: =IF(B23<>0,(C23-B23)/ABS(B23),0) -> -1
A24: Julho | B24: =SUMPRODUCT((BD_LUCRO!B2:B202=2025)*(MONTH(BD_LUCRO!C2:C202)=7)*IF(ISNUMBER(BD_LUCRO!O2:O202),BD_LUCRO!O2:O202,0)) -> 93877.56 | C24: =SUMPRODUCT((BD_LUCRO!B2:B202=2026)*(MONTH(BD_LUCRO!C2:C202)=7)*IF(ISNUMBER(BD_LUCRO!O2:O202),BD_LUCRO!O2:O202,0)) -> 0 | D24: =C24-B24 -> -93877.56 | E24: =IF(B24<>0,(C24-B24)/ABS(B24),0) -> -1
A25: Agosto | B25: =SUMPRODUCT((BD_LUCRO!B2:B202=2025)*(MONTH(BD_LUCRO!C2:C202)=8)*IF(ISNUMBER(BD_LUCRO!O2:O202),BD_LUCRO!O2:O202,0)) -> 357771.6 | C25: =SUMPRODUCT((BD_LUCRO!B2:B202=2026)*(MONTH(BD_LUCRO!C2:C202)=8)*IF(ISNUMBER(BD_LUCRO!O2:O202),BD_LUCRO!O2:O202,0)) -> 0 | D25: =C25-B25 -> -357771.6 | E25: =IF(B25<>0,(C25-B25)/ABS(B25),0) -> -1
A26: Setembro | B26: =SUMPRODUCT((BD_LUCRO!B2:B202=2025)*(MONTH(BD_LUCRO!C2:C202)=9)*IF(ISNUMBER(BD_LUCRO!O2:O202),BD_LUCRO!O2:O202,0)) -> 207587.74 | C26: =SUMPRODUCT((BD_LUCRO!B2:B202=2026)*(MONTH(BD_LUCRO!C2:C202)=9)*IF(ISNUMBER(BD_LUCRO!O2:O202),BD_LUCRO!O2:O202,0)) -> 0 | D26: =C26-B26 -> -207587.74 | E26: =IF(B26<>0,(C26-B26)/ABS(B26),0) -> -1
A27: Outubro | B27: =SUMPRODUCT((BD_LUCRO!B2:B202=2025)*(MONTH(BD_LUCRO!C2:C202)=10)*IF(ISNUMBER(BD_LUCRO!O2:O202),BD_LUCRO!O2:O202,0)) -> 233803.58 | C27: =SUMPRODUCT((BD_LUCRO!B2:B202=2026)*(MONTH(BD_LUCRO!C2:C202)=10)*IF(ISNUMBER(BD_LUCRO!O2:O202),BD_LUCRO!O2:O202,0)) -> 0 | D27: =C27-B27 -> -233803.58 | E27: =IF(B27<>0,(C27-B27)/ABS(B27),0) -> -1
A28: Novembro | B28: =SUMPRODUCT((BD_LUCRO!B2:B202=2025)*(MONTH(BD_LUCRO!C2:C202)=11)*IF(ISNUMBER(BD_LUCRO!O2:O202),BD_LUCRO!O2:O202,0)) -> 165851.95 | C28: =SUMPRODUCT((BD_LUCRO!B2:B202=2026)*(MONTH(BD_LUCRO!C2:C202)=11)*IF(ISNUMBER(BD_LUCRO!O2:O202),BD_LUCRO!O2:O202,0)) -> 0 | D28: =C28-B28 -> -165851.95 | E28: =IF(B28<>0,(C28-B28)/ABS(B28),0) -> -1
A29: Dezembro | B29: =SUMPRODUCT((BD_LUCRO!B2:B202=2025)*(MONTH(BD_LUCRO!C2:C202)=12)*IF(ISNUMBER(BD_LUCRO!O2:O202),BD_LUCRO!O2:O202,0)) -> 84051.78 | C29: =SUMPRODUCT((BD_LUCRO!B2:B202=2026)*(MONTH(BD_LUCRO!C2:C202)=12)*IF(ISNUMBER(BD_LUCRO!O2:O202),BD_LUCRO!O2:O202,0)) -> 0 | D29: =C29-B29 -> -84051.78 | E29: =IF(B29<>0,(C29-B29)/ABS(B29),0) -> -1
A30: TOTAL ANUAL | B30: =SUM(B18:B29) -> 4200075.4 | C30: =SUM(C18:C29) -> 1275125.2 | D30: =SUM(D18:D29) -> -2924950.3 | E30: =IF(B30<>0,(C30-B30)/ABS(B30),0) -> -0.69640423

Sheet BD_LUCRO
A1: Empresa | B1: Ano | C1: Mês | D1: Contrato V | E1: Contrato C | F1: Fornecedor | G1: Cliente | H1: Produto | I1: Peso Kg | J1: Sacas/Ton | K1: Lucro Bruto | L1: Total Frete | M1: Impostos | N1: Comissão | O1: Lucro Líq. | P1: Lucro Sc/Tn
A2: MM | B2: 2025 | C2: 45658 | D2: 0194/25 - SO | E2: 0195/25 - SO | F2: ANACLETO BRUNETTA E OUTROS | G2: ENGELHART CTP BRASIL S.A. | H2: SOJA EM GRAOS | I2: 558840 | J2: =I2/60 -> 9314 | K2: 138070 | L2: 94425.6 | M2: 0 | N2: 5658.25 | O2: 37986.15 | P2: =BD_LUCRO[[#This Row],[Lucro Líq.]]/BD_LUCRO[[#This Row],[Sacas/Ton]] -> 4.0783927
A3: MM | B3: 2025 | C3: 45658 | D3: 0198/25 - SO | E3: 0197/25 - SO | F3: IVETE TEREZINHA GALLO | G3: LOUIS DREYFUS COMPANY BRASIL S.A. | H3: SOJA EM GRAOS | I3: 413950 | J3: =I3/60 -> 6899.1667 | K3: 34495.83 | L3: 0 | M3: 0 | N3: 2069.75 | O3: 32426.08 | P3: =BD_LUCRO[[#This Row],[Lucro Líq.]]/BD_LUCRO[[#This Row],[Sacas/Ton]] -> 4.6999995
A4: MM | B4: 2025 | C4: 45658 | D4: 0199/25 - SO | E4: 0195/25 - SO | F4: ANACLETO BRUNETTA E OUTROS | G4: ENGELHART CTP (BRASIL) S.A. | H4: SOJA EM GRAOS | I4: 309400 | J4: =I4/60 -> 5156.6667 | K4: 110649.6 | L4: 81294.4 | M4: 0 | N4: 3145.57 | O4: 23867.52 | P4: =BD_LUCRO[[#This Row],[Lucro Líq.]]/BD_LUCRO[[#This Row],[Sacas/Ton]] -> 4.6284783
A5: MM | B5: 2025 | C5: 45689 | D5: - | E5: 0204/25 - POP | F5: SOMAR AGRONEGOCIOS EIRELLI ME | G5: - | H5: POP QUIMAR 164 | I5: 40 | J5: =I5/60 -> 0.66666667 | K5: 0 | L5: 0 | M5: 0 | N5: 0 | O5: 0 | P5: =BD_LUCRO[[#This Row],[Lucro Líq.]]/BD_LUCRO[[#This Row],[Sacas/Ton]] -> 0
A6: MM | B6: 2025 | C6: 45689 | D6: 0188/24 - SO | E6: 0179/24 - SO | F6: RICARDO PANCOTTE | G6: BUNGE ALIMENTOS S/A | H6: SOJA EM GRAOS | I6: 134954 | J6: =I6/60 -> 2249.2333 | K6: 61086.48 | L6: 0 | M6: 0 | N6: 1124.62 | O6: 59961.86 | P6: =BD_LUCRO[[#This Row],[Lucro Líq.]]/BD_LUCRO[[#This Row],[Sacas/Ton]] -> 26.658799
A7: MM | B7: 2025 | C7: 45689 | D7: 0191/25 - SO | E7: 0179/24 - SO | F7: RICARDO PANCOTTE | G7: LOUIS DREYFUS COMPANY BRASIL S.A. | H7: SOJA EM GRAOS | I7: 222150 | J7: =I7/60 -> 3702.5 | K7: 106439.1 | L7: 0 | M7: 0 | N7: 1851.25 | O7: 104587.85 | P7: =BD_LUCRO[[#This Row],[Lucro Líq.]]/BD_LUCRO[[#This Row],[Sacas/Ton]] -> 28.2479
A8: MM | B8: 2025 | C8: 45689 | D8: 0192/25 - SO | E8: 0177/24 - SO | F8: SILVIO CESAR VERDELIO E OUTRO | G8: AMAGGI EXPORTACAO E IMPORTACAO LTDA | H8: SOJA EM GRAOS | I8: 498138 | J8: =I8/60 -> 8302.3 | K8: 263630.4 | L8: 0 | M8: 0 | N8: 4151.15 | O8: 259479.25 | P8: =BD_LUCRO[[#This Row],[Lucro Líq.]]/BD_LUCRO[[#This Row],[Sacas/Ton]] -> 31.2539
A9: MM | B9: 2025 | C9: 45689 | D9: 0196/25 - SO | E9: 0200/25 - SO | F9: FERNANDO CESAR FACHOLLI | G9: LOUIS DREYFUS COMPANY BRASIL S.A. | H9: SOJA EM GRAOS | I9: 98041 | J9: =I9/60 -> 1634.0167 | K9: 31373.12 | L9: 0 | M9: 0 | N9: 490.21 | O9: 30882.92 | P9: =BD_LUCRO[[#This Row],[Lucro Líq.]]/BD_LUCRO[[#This Row],[Sacas/Ton]] -> 18.900003
A10: MM | B10: 2025 | C10: 45689 | D10: 0196/25 - SO | E10: 0201/25 - SO | F10: IVETE TEREZINHA GALLO | G10: LOUIS DREYFUS COMPANY BRASIL S.A. | H10: SOJA EM GRAOS | I10: 33405 | J10: =I10/60 -> 556.75 | K10: 4175.63 | L10: 0 | M10: 0 | N10: 167.03 | O10: 4008.6 | P10: =BD_LUCRO[[#This Row],[Lucro Líq.]]/BD_LUCRO[[#This Row],[Sacas/Ton]] -> 7.2
A11: MM | B11: 2025 | C11: 45689 | D11: 0196/25 - SO | E11: 0179/24 - SO | F11: RICARDO PANCOTTE | G11: LOUIS DREYFUS COMPANY BRASIL S.A. | H11: SOJA EM GRAOS | I11: 418009 | J11: =I11/60 -> 6966.8167 | K11: 217698.39 | L11: 0 | M11: 0 | N11: 3483.41 | O11: 214214.98 | P11: =BD_LUCRO[[#This Row],[Lucro Líq.]]/BD_LUCRO[[#This Row],[Sacas/Ton]] -> 30.7479
A12: MM | B12: 2025 | C12: 45689 | D12: 0196/25 - SO | E12: 0177/24 - SO | F12: SILVIO CESAR VERDELIO E OUTRO | G12: LOUIS DREYFUS COMPANY BRASIL S.A. | H12: SOJA EM GRAOS | I12: 50545 | J12: =I12/60 -> 842.41667 | K12: 28856.06 | L12: 0 | M12: 0 | N12: 252.73 | O12: 28603.33 | P12: =BD_LUCRO[[#This Row],[Lucro Líq.]]/BD_LUCRO[[#This Row],[Sacas/Ton]] -> 33.953899
A13: MM | B13: 2025 | C13: 45689 | D13: 0198/25 - SO | E13: 0197/25 - SO | F13: IVETE TEREZINHA GALLO | G13: LOUIS DREYFUS COMPANY BRASIL S.A. | H13: SOJA EM GRAOS | I13: 186050 | J13: =I13/60 -> 3100.8333 | K13: 15504.17 | L13: 0 | M13: 0 | N13: 930.25 | O13: 14573.92 | P13: =BD_LUCRO[[#This Row],[Lucro Líq.]]/BD_LUCRO[[#This Row],[Sacas/Ton]] -> 4.7000011
... A202: MM | B202: 2026 | C202: 46082 | D202: 0270/26 - FC | E202: 0269/26 - FC | F202: BELA CEREAIS COMERCIO LTDA. | G202: MARCIO VICTOR BELOTI | H202: FEIJAO CAUPI | I202: 18808 | J202: =I202/60 -> 313.46667 | K202: 0 | L202: 0 | M202: 0 | N202: 0 | O202: 0 | P202: =BD_LUCRO[[#This Row],[Lucro Líq.]]/BD_LUCRO[[#This Row],[Sacas/Ton]] -> 0
A203: Total | I203: =SUBTOTAL(109,BD_LUCRO[Peso Kg]) -> 34369181 | J203: =SUBTOTAL(109,BD_LUCRO[Sacas/Ton]) -> 572819.68 | K203: =SUBTOTAL(109,BD_LUCRO[Lucro Bruto]) -> 8741030.9 | L203: =SUBTOTAL(109,BD_LUCRO[Total Frete]) -> 3417848.8 | M203: =SUBTOTAL(109,BD_LUCRO[Impostos]) -> 68115.56 | N203: =SUBTOTAL(109,BD_LUCRO[Comissão]) -> 1981067.5 | O203: =SUBTOTAL(109,BD_LUCRO[Lucro Líq.]) -> 5475200.6 | P203: =SUBTOTAL(109,BD_LUCRO[Lucro Sc/Tn]) -> -91.750029

Sheet BD_DESP
A1: Empresa | B1: Ano | C1: Mês | D1: Item | E1: Valor
A2: MM | B2: 2025 | C2: 45658 | D2: CSLL | E2: 26408.69
A3: MM | B3: 2025 | C3: 45658 | D3: CUSTAS CARTORIAIS | E3: 118.5
A4: MM | B4: 2025 | C4: 45658 | D4: ENERGIA | E4: 890.23
A5: MM | B5: 2025 | C5: 45658 | D5: HONORARIO CONTABEL | E5: 1518
A6: MM | B6: 2025 | C6: 45658 | D6: INFORMATICA | E6: 84
A7: MM | B7: 2025 | C7: 45658 | D7: INSS | E7: 813.97
A8: MM | B8: 2025 | C8: 45658 | D8: INTERNET | E8: 179.9
A9: MM | B9: 2025 | C9: 45658 | D9: IOF | E9: 191.89
A10: MM | B10: 2025 | C10: 45658 | D10: IRPF | E10: 52501.37
A11: MM | B11: 2025 | C11: 45658 | D11: IRPJ | E11: 2887.53
A12: MM | B12: 2025 | C12: 45658 | D12: JUROS EMPRESTIMOS | E12: 10422.03
A13: MM | B13: 2025 | C13: 45658 | D13: OUTROS IMPOSTOS E TAXAS | E13: 112
... A663: BC_FILIAL | B663: 2026 | C663: 46082 | D663: DIVERSOS | E663: 675
A664: Total | E664: =SUBTOTAL(109,BD_DESP[Valor]) -> 4404361.4

Sheet HIST. MENSAL
B2: GRUPO | E2: BELA CEREAIS | H2: MM
B3: Resumo Global | E3: Resumo Global | H3: Resumo Global
B4: Lucro Bruto (Contratos) | C4: =BD_LUCRO[[#Totals],[Lucro Bruto]] -> 8741030.9 | E4: Lucro Bruto (Contratos) | H4: Lucro Bruto (Contratos)
B5: (-) Total Frete | C5: =-BD_LUCRO[[#Totals],[Total Frete]] -> -3417848.8 | E5: (-) Total Frete | H5: (-) Total Frete
B6: (-) Impostos Contratos | C6: =-BD_LUCRO[[#Totals],[Impostos]] -> -68115.56 | E6: (-) Impostos Contratos | H6: (-) Impostos Contratos
B7: (-) Comissões | C7: =-BD_LUCRO[[#Totals],[Comissão]] -> -1981067.5 | E7: (-) Comissões | H7: (-) Comissões
B8: (=) Lucro Líquido Operacional | C8: =BD_LUCRO[[#Totals],[Lucro Líq.]] -> 5475200.6 | E8: (=) Lucro Líquido Operacional | H8: (=) Lucro Líquido Operacional
B9: (-) Despesas Administrativas | C9: =-BD_DESP[[#Totals],[Valor]] -> -4404361.4 | E9: (-) Despesas Administrativas | H9: (-) Despesas Administrativas
B10: (=) LUCRO LÍQUIDO FINAL | C10: =C8+C9 -> 1070839.2 | E10: (=) LUCRO LÍQUIDO FINAL | F10: =F8+F9 -> 0 | H10: (=) LUCRO LÍQUIDO FINAL | I10: =I8+I9 -> 0
B12: HISTORICO MENSAL GRUPO 2025
B13: Mês | C13: Qtde Contratos | D13: Peso Kg Total | E13: Lucro Bruto | F13: Total Frete | G13: Impostos Cont. | H13: Comissões | I13: Luc. Liq. Oper. | J13: Desp. Admin. | K13: Lucro Líq. Final | L13: Mg. Bruta % | M13: Mg. Líq. % | N13: Resultado | O13: Var. Mês Ant.
B14: Janeiro/2026 | C14: =COUNTIFS(BD_LUCRO[Mês],$B14) -> 20 | D14: =SUMIFS(BD_LUCRO[Peso Kg],BD_LUCRO[Mês],$B14) -> 1405762 | E14: =SUMIFS(BD_LUCRO[Lucro Bruto],BD_LUCRO[Mês],$B14) -> 396032.25 | F14: =SUMIFS(BD_LUCRO[Total Frete],BD_LUCRO[Mês],$B14) -> 103059.8 | G14: =SUMIFS(BD_LUCRO[Impostos],BD_LUCRO[Mês],$B14) -> 11250.02 | H14: =SUMIFS(BD_LUCRO[Comissão],BD_LUCRO[Mês],$B14) -> 18245.08 | I14: =SUMIFS(BD_LUCRO[Lucro Líq.],BD_LUCRO[Mês],$B14) -> 259819.54 | J14: =SUMIFS(BD_DESP[Valor],BD_DESP[Mês],$B14) -> 277928.94 | K14: =I14-J14 -> -18109.4 | L14: =IF(E14<>0,(E14-F14-G14-H14)/E14,0) -> 0.66529266 | M14: =IF(E14<>0,K14/E14,0) -> -0.045727084 | N14: =IF(COUNTIFS(BD_LUCRO[Mês],$B14)=0,"N/A",IF(K14>=0,"✅ POSITIVO","❌ NEGATIVO")) -> ❌ NEGATIVO | O14: -
B15: Fevereiro/2026 | C15: =COUNTIFS(BD_LUCRO[Mês],$B15) -> 36 | D15: =SUMIFS(BD_LUCRO[Peso Kg],BD_LUCRO[Mês],$B15) -> 3191522 | E15: =SUMIFS(BD_LUCRO[Lucro Bruto],BD_LUCRO[Mês],$B15) -> 598649.69 | F15: =SUMIFS(BD_LUCRO[Total Frete],BD_LUCRO[Mês],$B15) -> 37740.2 | G15: =SUMIFS(BD_LUCRO[Impostos],BD_LUCRO[Mês],$B15) -> 48781.22 | H15: =SUMIFS(BD_LUCRO[Comissão],BD_LUCRO[Mês],$B15) -> 67058.53 | I15: =SUMIFS(BD_LUCRO[Lucro Líq.],BD_LUCRO[Mês],$B15) -> 566766.6 | J15: =SUMIFS(BD_DESP[Valor],BD_DESP[Mês],$B15) -> 190770.48 | K15: =I15-J15 -> 375996.12 | L15: =IF(E15<>0,(E15-F15-G15-H15)/E15,0) -> 0.74345606 | M15: =IF(E15<>0,K15/E15,0) -> 0.62807369 | N15: =IF(COUNTIFS(BD_LUCRO[Mês],$B15)=0,"N/A",IF(K15>=0,"✅ POSITIVO","❌ NEGATIVO")) -> ✅ POSITIVO | O15: =IF(C15=0,0,IF(OR(C14=0,K14=0),0,(K15-K14)/ABS(K14))) -> 21.762484
B16: Março/2026 | C16: =COUNTIFS(BD_LUCRO[Mês],$B16) -> 21 | D16: =SUMIFS(BD_LUCRO[Peso Kg],BD_LUCRO[Mês],$B16) -> 4055398 | E16: =SUMIFS(BD_LUCRO[Lucro Bruto],BD_LUCRO[Mês],$B16) -> 780396.29 | F16: =SUMIFS(BD_LUCRO[Total Frete],BD_LUCRO[Mês],$B16) -> 17877 | G16: =SUMIFS(BD_LUCRO[Impostos],BD_LUCRO[Mês],$B16) -> 802.35 | H16: =SUMIFS(BD_LUCRO[Comissão],BD_LUCRO[Mês],$B16) -> 69624.03 | I16: =SUMIFS(BD_LUCRO[Lucro Líq.],BD_LUCRO[Mês],$B16) -> 448539.01 | J16: =SUMIFS(BD_DESP[Valor],BD_DESP[Mês],$B16) -> 258155.2 | K16: =I16-J16 -> 190383.81 | L16: =IF(E16<>0,(E16-F16-G16-H16)/E16,0) -> 0.88684803 | M16: =IF(E16<>0,K16/E16,0) -> 0.24395786 | N16: =IF(COUNTIFS(BD_LUCRO[Mês],$B16)=0,"N/A",IF(K16>=0,"✅ POSITIVO","❌ NEGATIVO")) -> ✅ POSITIVO | O16: =IF(C16=0,0,IF(OR(C15=0,K15=0),0,(K16-K15)/ABS(K15))) -> -0.49365485
B17: Abril/2026 | C17: =COUNTIFS(BD_LUCRO[Mês],$B17) -> 0 | D17: =SUMIFS(BD_LUCRO[Peso Kg],BD_LUCRO[Mês],$B17) -> 0 | E17: =SUMIFS(BD_LUCRO[Lucro Bruto],BD_LUCRO[Mês],$B17) -> 0 | F17: =SUMIFS(BD_LUCRO[Total Frete],BD_LUCRO[Mês],$B17) -> 0 | G17: =SUMIFS(BD_LUCRO[Impostos],BD_LUCRO[Mês],$B17) -> 0 | H17: =SUMIFS(BD_LUCRO[Comissão],BD_LUCRO[Mês],$B17) -> 0 | I17: =SUMIFS(BD_LUCRO[Lucro Líq.],BD_LUCRO[Mês],$B17) -> 0 | J17: =SUMIFS(BD_DESP[Valor],BD_DESP[Mês],$B17) -> 0 | K17: =I17-J17 -> 0 | L17: =IF(E17<>0,(E17-F17-G17-H17)/E17,0) -> 0 | M17: =IF(E17<>0,K17/E17,0) -> 0 | N17: =IF(COUNTIFS(BD_LUCRO[Mês],$B17)=0,"N/A",IF(K17>=0,"✅ POSITIVO","❌ NEGATIVO")) -> N/A | O17: =IF(C17=0,0,IF(OR(C16=0,K16=0),0,(K17-K16)/ABS(K16))) -> 0
B18: Maio/2026 | C18: =COUNTIFS(BD_LUCRO[Mês],$B18) -> 0 | D18: =SUMIFS(BD_LUCRO[Peso Kg],BD_LUCRO[Mês],$B18) -> 0 | E18: =SUMIFS(BD_LUCRO[Lucro Bruto],BD_LUCRO[Mês],$B18) -> 0 | F18: =SUMIFS(BD_LUCRO[Total Frete],BD_LUCRO[Mês],$B18) -> 0 | G18: =SUMIFS(BD_LUCRO[Impostos],BD_LUCRO[Mês],$B18) -> 0 | H18: =SUMIFS(BD_LUCRO[Comissão],BD_LUCRO[Mês],$B18) -> 0 | I18: =SUMIFS(BD_LUCRO[Lucro Líq.],BD_LUCRO[Mês],$B18) -> 0 | J18: =SUMIFS(BD_DESP[Valor],BD_DESP[Mês],$B18) -> 0 | K18: =I18-J18 -> 0 | L18: =IF(E18<>0,(E18-F18-G18-H18)/E18,0) -> 0 | M18: =IF(E18<>0,K18/E18,0) -> 0 | N18: =IF(COUNTIFS(BD_LUCRO[Mês],$B18)=0,"N/A",IF(K18>=0,"✅ POSITIVO","❌ NEGATIVO")) -> N/A | O18: =IF(C18=0,0,IF(OR(C17=0,K17=0),0,(K18-K17)/ABS(K17))) -> 0
B19: Junho/2026 | C19: =COUNTIFS(BD_LUCRO[Mês],$B19) -> 0 | D19: =SUMIFS(BD_LUCRO[Peso Kg],BD_LUCRO[Mês],$B19) -> 0 | E19: =SUMIFS(BD_LUCRO[Lucro Bruto],BD_LUCRO[Mês],$B19) -> 0 | F19: =SUMIFS(BD_LUCRO[Total Frete],BD_LUCRO[Mês],$B19) -> 0 | G19: =SUMIFS(BD_LUCRO[Impostos],BD_LUCRO[Mês],$B19) -> 0 | H19: =SUMIFS(BD_LUCRO[Comissão],BD_LUCRO[Mês],$B19) -> 0 | I19: =SUMIFS(BD_LUCRO[Lucro Líq.],BD_LUCRO[Mês],$B19) -> 0 | J19: =SUMIFS(BD_DESP[Valor],BD_DESP[Mês],$B19) -> 0 | K19: =I19-J19 -> 0 | L19: =IF(E19<>0,(E19-F19-G19-H19)/E19,0) -> 0 | M19: =IF(E19<>0,K19/E19,0) -> 0 | N19: =IF(COUNTIFS(BD_LUCRO[Mês],$B19)=0,"N/A",IF(K19>=0,"✅ POSITIVO","❌ NEGATIVO")) -> N/A | O19: =IF(C19=0,0,IF(OR(C18=0,K18=0),0,(K19-K18)/ABS(K18))) -> 0
B20: Julho/2026 | C20: =COUNTIFS(BD_LUCRO[Mês],$B20) -> 0 | D20: =SUMIFS(BD_LUCRO[Peso Kg],BD_LUCRO[Mês],$B20) -> 0 | E20: =SUMIFS(BD_LUCRO[Lucro Bruto],BD_LUCRO[Mês],$B20) -> 0 | F20: =SUMIFS(BD_LUCRO[Total Frete],BD_LUCRO[Mês],$B20) -> 0 | G20: =SUMIFS(BD_LUCRO[Impostos],BD_LUCRO[Mês],$B20) -> 0 | H20: =SUMIFS(BD_LUCRO[Comissão],BD_LUCRO[Mês],$B20) -> 0 | I20: =SUMIFS(BD_LUCRO[Lucro Líq.],BD_LUCRO[Mês],$B20) -> 0 | J20: =SUMIFS(BD_DESP[Valor],BD_DESP[Mês],$B20) -> 0 | K20: =I20-J20 -> 0 | L20: =IF(E20<>0,(E20-F20-G20-H20)/E20,0) -> 0 | M20: =IF(E20<>0,K20/E20,0) -> 0 | N20: =IF(COUNTIFS(BD_LUCRO[Mês],$B20)=0,"N/A",IF(K20>=0,"✅ POSITIVO","❌ NEGATIVO")) -> N/A | O20: =IF(C20=0,0,IF(OR(C19=0,K19=0),0,(K20-K19)/ABS(K19))) -> 0
B21: Agosto/2026 | C21: =COUNTIFS(BD_LUCRO[Mês],$B21) -> 0 | D21: =SUMIFS(BD_LUCRO[Peso Kg],BD_LUCRO[Mês],$B21) -> 0 | E21: =SUMIFS(BD_LUCRO[Lucro Bruto],BD_LUCRO[Mês],$B21) -> 0 | F21: =SUMIFS(BD_LUCRO[Total Frete],BD_LUCRO[Mês],$B21) -> 0 | G21: =SUMIFS(BD_LUCRO[Impostos],BD_LUCRO[Mês],$B21) -> 0 | H21: =SUMIFS(BD_LUCRO[Comissão],BD_LUCRO[Mês],$B21) -> 0 | I21: =SUMIFS(BD_LUCRO[Lucro Líq.],BD_LUCRO[Mês],$B21) -> 0 | J21: =SUMIFS(BD_DESP[Valor],BD_DESP[Mês],$B21) -> 0 | K21: =I21-J21 -> 0 | L21: =IF(E21<>0,(E21-F21-G21-H21)/E21,0) -> 0 | M21: =IF(E21<>0,K21/E21,0) -> 0 | N21: =IF(COUNTIFS(BD_LUCRO[Mês],$B21)=0,"N/A",IF(K21>=0,"✅ POSITIVO","❌ NEGATIVO")) -> N/A | O21: =IF(C21=0,0,IF(OR(C20=0,K20=0),0,(K21-K20)/ABS(K20))) -> 0
B22: Setembro/2026 | C22: =COUNTIFS(BD_LUCRO[Mês],$B22) -> 0 | D22: =SUMIFS(BD_LUCRO[Peso Kg],BD_LUCRO[Mês],$B22) -> 0 | E22: =SUMIFS(BD_LUCRO[Lucro Bruto],BD_LUCRO[Mês],$B22) -> 0 | F22: =SUMIFS(BD_LUCRO[Total Frete],BD_LUCRO[Mês],$B22) -> 0 | G22: =SUMIFS(BD_LUCRO[Impostos],BD_LUCRO[Mês],$B22) -> 0 | H22: =SUMIFS(BD_LUCRO[Comissão],BD_LUCRO[Mês],$B22) -> 0 | I22: =SUMIFS(BD_LUCRO[Lucro Líq.],BD_LUCRO[Mês],$B22) -> 0 | J22: =SUMIFS(BD_DESP[Valor],BD_DESP[Mês],$B22) -> 0 | K22: =I22-J22 -> 0 | L22: =IF(E22<>0,(E22-F22-G22-H22)/E22,0) -> 0 | M22: =IF(E22<>0,K22/E22,0) -> 0 | N22: =IF(COUNTIFS(BD_LUCRO[Mês],$B22)=0,"N/A",IF(K22>=0,"✅ POSITIVO","❌ NEGATIVO")) -> N/A | O22: =IF(C22=0,0,IF(OR(C21=0,K21=0),0,(K22-K21)/ABS(K21))) -> 0
B23: Outubro/2026 | C23: =COUNTIFS(BD_LUCRO[Mês],$B23) -> 0 | D23: =SUMIFS(BD_LUCRO[Peso Kg],BD_LUCRO[Mês],$B23) -> 0 | E23: =SUMIFS(BD_LUCRO[Lucro Bruto],BD_LUCRO[Mês],$B23) -> 0 | F23: =SUMIFS(BD_LUCRO[Total Frete],BD_LUCRO[Mês],$B23) -> 0 | G23: =SUMIFS(BD_LUCRO[Impostos],BD_LUCRO[Mês],$B23) -> 0 | H23: =SUMIFS(BD_LUCRO[Comissão],BD_LUCRO[Mês],$B23) -> 0 | I23: =SUMIFS(BD_LUCRO[Lucro Líq.],BD_LUCRO[Mês],$B23) -> 0 | J23: =SUMIFS(BD_DESP[Valor],BD_DESP[Mês],$B23) -> 0 | K23: =I23-J23 -> 0 | L23: =IF(E23<>0,(E23-F23-G23-H23)/E23,0) -> 0 | M23: =IF(E23<>0,K23/E23,0) -> 0 | N23: =IF(COUNTIFS(BD_LUCRO[Mês],$B23)=0,"N/A",IF(K23>=0,"✅ POSITIVO","❌ NEGATIVO")) -> N/A | O23: =IF(C23=0,0,IF(OR(C22=0,K22=0),0,(K23-K22)/ABS(K22))) -> 0
B24: Novembro/2026 | C24: =COUNTIFS(BD_LUCRO[Mês],$B24) -> 0 | D24: =SUMIFS(BD_LUCRO[Peso Kg],BD_LUCRO[Mês],$B24) -> 0 | E24: =SUMIFS(BD_LUCRO[Lucro Bruto],BD_LUCRO[Mês],$B24) -> 0 | F24: =SUMIFS(BD_LUCRO[Total Frete],BD_LUCRO[Mês],$B24) -> 0 | G24: =SUMIFS(BD_LUCRO[Impostos],BD_LUCRO[Mês],$B24) -> 0 | H24: =SUMIFS(BD_LUCRO[Comissão],BD_LUCRO[Mês],$B24) -> 0 | I24: =SUMIFS(BD_LUCRO[Lucro Líq.],BD_LUCRO[Mês],$B24) -> 0 | J24: =SUMIFS(BD_DESP[Valor],BD_DESP[Mês],$B24) -> 0 | K24: =I24-J24 -> 0 | L24: =IF(E24<>0,(E24-F24-G24-H24)/E24,0) -> 0 | M24: =IF(E24<>0,K24/E24,0) -> 0 | N24: =IF(COUNTIFS(BD_LUCRO[Mês],$B24)=0,"N/A",IF(K24>=0,"✅ POSITIVO","❌ NEGATIVO")) -> N/A | O24: =IF(C24=0,0,IF(OR(C23=0,K23=0),0,(K24-K23)/ABS(K23))) -> 0
B25: Dezembro/2026 | C25: =COUNTIFS(BD_LUCRO[Mês],$B25) -> 0 | D25: =SUMIFS(BD_LUCRO[Peso Kg],BD_LUCRO[Mês],$B25) -> 0 | E25: =SUMIFS(BD_LUCRO[Lucro Bruto],BD_LUCRO[Mês],$B25) -> 0 | F25: =SUMIFS(BD_LUCRO[Total Frete],BD_LUCRO[Mês],$B25) -> 0 | G25: =SUMIFS(BD_LUCRO[Impostos],BD_LUCRO[Mês],$B25) -> 0 | H25: =SUMIFS(BD_LUCRO[Comissão],BD_LUCRO[Mês],$B25) -> 0 | I25: =SUMIFS(BD_LUCRO[Lucro Líq.],BD_LUCRO[Mês],$B25) -> 0 | J25: =SUMIFS(BD_DESP[Valor],BD_DESP[Mês],$B25) -> 0 | K25: =I25-J25 -> 0 | L25: =IF(E25<>0,(E25-F25-G25-H25)/E25,0) -> 0 | M25: =IF(E25<>0,K25/E25,0) -> 0 | N25: =IF(COUNTIFS(BD_LUCRO[Mês],$B25)=0,"N/A",IF(K25>=0,"✅ POSITIVO","❌ NEGATIVO")) -> N/A | O25: =IF(C25=0,0,IF(OR(C24=0,K24=0),0,(K25-K24)/ABS(K24))) -> 0
B26: TOTAL ANUAL 2026 | C26: =SUM(C14:C25) -> 77 | D26: =SUM(D14:D25) -> 8652682 | E26: =SUM(E14:E25) -> 1775078.2 | F26: =SUM(F14:F25) -> 158677 | G26: =SUM(G14:G25) -> 60833.59 | H26: =SUM(H14:H25) -> 154927.64 | I26: =SUM(I14:I25) -> 1275125.2 | J26: =SUM(J14:J25) -> 726854.62 | K26: =SUM(K14:K25) -> 548270.53 | L26: =IF(E26<>0,(E26-F26-G26-H26)/E26,0) -> 0.78905818 | M26: =IF(E26<>0,K26/E26,0) -> 0.30887119 | N26: =IF(K26>=0,"✅ POSITIVO","❌ NEGATIVO") -> ✅ POSITIVO | O26: -
B28: HISTÓRICO MENSAL GRUPO 2025
B29: Mês | C29: Qtde Contratos | D29: Peso Kg Total | E29: Lucro Bruto | F29: Total Frete | G29: Impostos Cont. | H29: Comissões | I29: Luc. Liq. Oper. | J29: Desp. Admin. | K29: Lucro Líq. Final | L29: Mg. Bruta % | M29: Mg. Líq. % | N29: Resultado | O29: Var. Mês Ant.
B30: Janeiro/2025 | C30: =COUNTIFS(BD_LUCRO[Mês],$B30) -> 5 | D30: =SUMIFS(BD_LUCRO[Peso Kg],BD_LUCRO[Mês],$B30) -> 1446450 | E30: =SUMIFS(BD_LUCRO[Lucro Bruto],BD_LUCRO[Mês],$B30) -> 347078.94 | F30: =SUMIFS(BD_LUCRO[Total Frete],BD_LUCRO[Mês],$B30) -> 212796.84 | G30: =SUMIFS(BD_LUCRO[Impostos],BD_LUCRO[Mês],$B30) -> 3518.06 | H30: =SUMIFS(BD_LUCRO[Comissão],BD_LUCRO[Mês],$B30) -> 11539.87 | I30: =SUMIFS(BD_LUCRO[Lucro Líq.],BD_LUCRO[Mês],$B30) -> 106231.7 | J30: =SUMIFS(BD_DESP[Valor],BD_DESP[Mês],$B30) -> 267317.77 | K30: =I30-J30 -> -161086.07 | L30: =IF(E30<>0,(E30-F30-G30-H30)/E30,0) -> 0.34350736 | M30: =IF(E30<>0,K30/E30,0) -> -0.4641194 | N30: =IF(COUNTIFS(BD_LUCRO[Mês],$B30)=0,"N/A",IF(K30>=0,"✅ POSITIVO","❌ NEGATIVO")) -> ❌ NEGATIVO | O30: -
B31: Fevereiro/2025 | C31: =COUNTIFS(BD_LUCRO[Mês],$B31) -> 13 | D31: =SUMIFS(BD_LUCRO[Peso Kg],BD_LUCRO[Mês],$B31) -> 1787495 | E31: =SUMIFS(BD_LUCRO[Lucro Bruto],BD_LUCRO[Mês],$B31) -> 781745.28 | F31: =SUMIFS(BD_LUCRO[Total Frete],BD_LUCRO[Mês],$B31) -> 0 | G31: =SUMIFS(BD_LUCRO[Impostos],BD_LUCRO[Mês],$B31) -> 1064.6 | H31: =SUMIFS(BD_LUCRO[Comissão],BD_LUCRO[Mês],$B31) -> 13556.84 | I31: =SUMIFS(BD_LUCRO[Lucro Líq.],BD_LUCRO[Mês],$B31) -> 716883.4 | J31: =SUMIFS(BD_DESP[Valor],BD_DESP[Mês],$B31) -> 142974.87 | K31: =I31-J31 -> 573908.53 | L31: =IF(E31<>0,(E31-F31-G31-H31)/E31,0) -> 0.98129641 | M31: =IF(E31<>0,K31/E31,0) -> 0.73413751 | N31: =IF(COUNTIFS(BD_LUCRO[Mês],$B31)=0,"N/A",IF(K31>=0,"✅ POSITIVO","❌ NEGATIVO")) -> ✅ POSITIVO | O31: =IF(K30<>0,(K31-K30)/ABS(K30),0) -> 4.5627446
B32: Março/2025 | C32: =COUNTIFS(BD_LUCRO[Mês],$B32) -> 18 | D32: =SUMIFS(BD_LUCRO[Peso Kg],BD_LUCRO[Mês],$B32) -> 3981807 | E32: =SUMIFS(BD_LUCRO[Lucro Bruto],BD_LUCRO[Mês],$B32) -> 1689268 | F32: =SUMIFS(BD_LUCRO[Total Frete],BD_LUCRO[Mês],$B32) -> 432839.6 | G32: =SUMIFS(BD_LUCRO[Impostos],BD_LUCRO[Mês],$B32) -> 0 | H32: =SUMIFS(BD_LUCRO[Comissão],BD_LUCRO[Mês],$B32) -> 99575.07 | I32: =SUMIFS(BD_LUCRO[Lucro Líq.],BD_LUCRO[Mês],$B32) -> 1154496.8 | J32: =SUMIFS(BD_DESP[Valor],BD_DESP[Mês],$B32) -> 180047.93 | K32: =I32-J32 -> 974448.91 | L32: =IF(E32<>0,(E32-F32-G32-H32)/E32,0) -> 0.68482521 | M32: =IF(E32<>0,K32/E32,0) -> 0.57684686 | N32: =IF(COUNTIFS(BD_LUCRO[Mês],$B32)=0,"N/A",IF(K32>=0,"✅ POSITIVO","❌ NEGATIVO")) -> ✅ POSITIVO | O32: =IF(K31<>0,(K32-K31)/ABS(K31),0) -> 0.69791676
B33: Abril/2025 | C33: =COUNTIFS(BD_LUCRO[Mês],$B33) -> 13 | D33: =SUMIFS(BD_LUCRO[Peso Kg],BD_LUCRO[Mês],$B33) -> 4701587 | E33: =SUMIFS(BD_LUCRO[Lucro Bruto],BD_LUCRO[Mês],$B33) -> 1264396.6 | F33: =SUMIFS(BD_LUCRO[Total Frete],BD_LUCRO[Mês],$B33) -> 623905.38 | G33: =SUMIFS(BD_LUCRO[Impostos],BD_LUCRO[Mês],$B33) -> 0 | H33: =SUMIFS(BD_LUCRO[Comissão],BD_LUCRO[Mês],$B33) -> 140516.21 | I33: =SUMIFS(BD_LUCRO[Lucro Líq.],BD_LUCRO[Mês],$B33) -> 499270.09 | J33: =SUMIFS(BD_DESP[Valor],BD_DESP[Mês],$B33) -> 354429.39 | K33: =I33-J33 -> 144840.7 | L33: =IF(E33<>0,(E33-F33-G33-H33)/E33,0) -> 0.39542576 | M33: =IF(E33<>0,K33/E33,0) -> 0.11455322 | N33: =IF(COUNTIFS(BD_LUCRO[Mês],$B33)=0,"N/A",IF(K33>=0,"✅ POSITIVO","❌ NEGATIVO")) -> ✅ POSITIVO | O33: =IF(K32<>0,(K33-K32)/ABS(K32),0) -> -0.85136142
B34: Maio/2025 | C34: =COUNTIFS(BD_LUCRO[Mês],$B34) -> 10 | D34: =SUMIFS(BD_LUCRO[Peso Kg],BD_LUCRO[Mês],$B34) -> 2738898 | E34: =SUMIFS(BD_LUCRO[Lucro Bruto],BD_LUCRO[Mês],$B34) -> 713587.7 | F34: =SUMIFS(BD_LUCRO[Total Frete],BD_LUCRO[Mês],$B34) -> 181454.79 | G34: =SUMIFS(BD_LUCRO[Impostos],BD_LUCRO[Mês],$B34) -> 637.16 | H34: =SUMIFS(BD_LUCRO[Comissão],BD_LUCRO[Mês],$B34) -> 19763.06 | I34: =SUMIFS(BD_LUCRO[Lucro Líq.],BD_LUCRO[Mês],$B34) -> 520095.42 | J34: =SUMIFS(BD_DESP[Valor],BD_DESP[Mês],$B34) -> 137831.58 | K34: =I34-J34 -> 382263.84 | L34: =IF(E34<>0,(E34-F34-G34-H34)/E34,0) -> 0.71712656 | M34: =IF(E34<>0,K34/E34,0) -> 0.53569287 | N34: =IF(COUNTIFS(BD_LUCRO[Mês],$B34)=0,"N/A",IF(K34>=0,"✅ POSITIVO","❌ NEGATIVO")) -> ✅ POSITIVO | O34: =IF(K33<>0,(K34-K33)/ABS(K33),0) -> 1.6392018
B35: Junho/2025 | C35: =COUNTIFS(BD_LUCRO[Mês],$B35) -> 8 | D35: =SUMIFS(BD_LUCRO[Peso Kg],BD_LUCRO[Mês],$B35) -> 1853380 | E35: =SUMIFS(BD_LUCRO[Lucro Bruto],BD_LUCRO[Mês],$B35) -> 92136.99 | F35: =SUMIFS(BD_LUCRO[Total Frete],BD_LUCRO[Mês],$B35) -> 351139.42 | G35: =SUMIFS(BD_LUCRO[Impostos],BD_LUCRO[Mês],$B35) -> 15779.23 | H35: =SUMIFS(BD_LUCRO[Comissão],BD_LUCRO[Mês],$B35) -> 197665.77 | I35: =SUMIFS(BD_LUCRO[Lucro Líq.],BD_LUCRO[Mês],$B35) -> 60153.78 | J35: =SUMIFS(BD_DESP[Valor],BD_DESP[Mês],$B35) -> 259224.64 | K35: =I35-J35 -> -199070.86 | L35: =IF(E35<>0,(E35-F35-G35-H35)/E35,0) -> -5.127663 | M35: =IF(E35<>0,K35/E35,0) -> -2.1605965 | N35: =IF(COUNTIFS(BD_LUCRO[Mês],$B35)=0,"N/A",IF(K35>=0,"✅ POSITIVO","❌ NEGATIVO")) -> ❌ NEGATIVO | O35: =IF(K34<>0,(K35-K34)/ABS(K34),0) -> -1.5207682
B36: Julho/2025 | C36: =COUNTIFS(BD_LUCRO[Mês],$B36) -> 5 | D36: =SUMIFS(BD_LUCRO[Peso Kg],BD_LUCRO[Mês],$B36) -> 754300 | E36: =SUMIFS(BD_LUCRO[Lucro Bruto],BD_LUCRO[Mês],$B36) -> 0 | F36: =SUMIFS(BD_LUCRO[Total Frete],BD_LUCRO[Mês],$B36) -> 242622.45 | G36: =SUMIFS(BD_LUCRO[Impostos],BD_LUCRO[Mês],$B36) -> -69880.18 | H36: =SUMIFS(BD_LUCRO[Comissão],BD_LUCRO[Mês],$B36) -> 393437.97 | I36: =SUMIFS(BD_LUCRO[Lucro Líq.],BD_LUCRO[Mês],$B36) -> 93877.56 | J36: =SUMIFS(BD_DESP[Valor],BD_DESP[Mês],$B36) -> 713342.74 | K36: =I36-J36 -> -619465.18 | L36: =IF(E36<>0,(E36-F36-G36-H36)/E36,0) -> 0 | M36: =IF(E36<>0,K36/E36,0) -> 0 | N36: =IF(COUNTIFS(BD_LUCRO[Mês],$B36)=0,"N/A",IF(K36>=0,"✅ POSITIVO","❌ NEGATIVO")) -> ❌ NEGATIVO | O36: =IF(K35<>0,(K36-K35)/ABS(K35),0) -> -2.1117823
B37: Agosto/2025 | C37: =COUNTIFS(BD_LUCRO[Mês],$B37) -> 11 | D37: =SUMIFS(BD_LUCRO[Peso Kg],BD_LUCRO[Mês],$B37) -> 1484382 | E37: =SUMIFS(BD_LUCRO[Lucro Bruto],BD_LUCRO[Mês],$B37) -> 847503.9 | F37: =SUMIFS(BD_LUCRO[Total Frete],BD_LUCRO[Mês],$B37) -> 306565.3 | G37: =SUMIFS(BD_LUCRO[Impostos],BD_LUCRO[Mês],$B37) -> 6852.62 | H37: =SUMIFS(BD_LUCRO[Comissão],BD_LUCRO[Mês],$B37) -> 397616.86 | I37: =SUMIFS(BD_LUCRO[Lucro Líq.],BD_LUCRO[Mês],$B37) -> 357771.6 | J37: =SUMIFS(BD_DESP[Valor],BD_DESP[Mês],$B37) -> 480656.74 | K37: =I37-J37 -> -122885.14 | L37: =IF(E37<>0,(E37-F37-G37-H37)/E37,0) -> 0.16102477 | M37: =IF(E37<>0,K37/E37,0) -> -0.14499655 | N37: =IF(COUNTIFS(BD_LUCRO[Mês],$B37)=0,"N/A",IF(K37>=0,"✅ POSITIVO","❌ NEGATIVO")) -> ❌ NEGATIVO | O37: =IF(K36<>0,(K37-K36)/ABS(K36),0) -> 0.80162704
B38: Setembro/2025 | C38: =COUNTIFS(BD_LUCRO[Mês],$B38) -> 12 | D38: =SUMIFS(BD_LUCRO[Peso Kg],BD_LUCRO[Mês],$B38) -> 2623460 | E38: =SUMIFS(BD_LUCRO[Lucro Bruto],BD_LUCRO[Mês],$B38) -> 432526.47 | F38: =SUMIFS(BD_LUCRO[Total Frete],BD_LUCRO[Mês],$B38) -> 205826.1 | G38: =SUMIFS(BD_LUCRO[Impostos],BD_LUCRO[Mês],$B38) -> 14225.53 | H38: =SUMIFS(BD_LUCRO[Comissão],BD_LUCRO[Mês],$B38) -> 464.8 | I38: =SUMIFS(BD_LUCRO[Lucro Líq.],BD_LUCRO[Mês],$B38) -> 207587.74 | J38: =SUMIFS(BD_DESP[Valor],BD_DESP[Mês],$B38) -> 331951.65 | K38: =I38-J38 -> -124363.91 | L38: =IF(E38<>0,(E38-F38-G38-H38)/E38,0) -> 0.49016662 | M38: =IF(E38<>0,K38/E38,0) -> -0.28752902 | N38: =IF(COUNTIFS(BD_LUCRO[Mês],$B38)=0,"N/A",IF(K38>=0,"✅ POSITIVO","❌ NEGATIVO")) -> ❌ NEGATIVO | O38: =IF(K37<>0,(K38-K37)/ABS(K37),0) -> -0.012033758
B39: Outubro/2025 | C39: =COUNTIFS(BD_LUCRO[Mês],$B39) -> 12 | D39: =SUMIFS(BD_LUCRO[Peso Kg],BD_LUCRO[Mês],$B39) -> 1559400 | E39: =SUMIFS(BD_LUCRO[Lucro Bruto],BD_LUCRO[Mês],$B39) -> 193668.13 | F39: =SUMIFS(BD_LUCRO[Total Frete],BD_LUCRO[Mês],$B39) -> 279111.15 | G39: =SUMIFS(BD_LUCRO[Impostos],BD_LUCRO[Mês],$B39) -> 6172.99 | H39: =SUMIFS(BD_LUCRO[Comissão],BD_LUCRO[Mês],$B39) -> 541462.79 | I39: =SUMIFS(BD_LUCRO[Lucro Líq.],BD_LUCRO[Mês],$B39) -> 233803.58 | J39: =SUMIFS(BD_DESP[Valor],BD_DESP[Mês],$B39) -> 178639.79 | K39: =I39-J39 -> 55163.79 | L39: =IF(E39<>0,(E39-F39-G39-H39)/E39,0) -> -3.2688848 | M39: =IF(E39<>0,K39/E39,0) -> 0.28483669 | N39: =IF(COUNTIFS(BD_LUCRO[Mês],$B39)=0,"N/A",IF(K39>=0,"✅ POSITIVO","❌ NEGATIVO")) -> ✅ POSITIVO | O39: =IF(K38<>0,(K39-K38)/ABS(K38),0) -> 1.4435675
B40: Novembro/2025 | C40: =COUNTIFS(BD_LUCRO[Mês],$B40) -> 13 | D40: =SUMIFS(BD_LUCRO[Peso Kg],BD_LUCRO[Mês],$B40) -> 2024100 | E40: =SUMIFS(BD_LUCRO[Lucro Bruto],BD_LUCRO[Mês],$B40) -> 288046.53 | F40: =SUMIFS(BD_LUCRO[Total Frete],BD_LUCRO[Mês],$B40) -> 216594.87 | G40: =SUMIFS(BD_LUCRO[Impostos],BD_LUCRO[Mês],$B40) -> 14242.64 | H40: =SUMIFS(BD_LUCRO[Comissão],BD_LUCRO[Mês],$B40) -> 7019.6 | I40: =SUMIFS(BD_LUCRO[Lucro Líq.],BD_LUCRO[Mês],$B40) -> 165851.95 | J40: =SUMIFS(BD_DESP[Valor],BD_DESP[Mês],$B40) -> 325465.06 | K40: =I40-J40 -> -159613.11 | L40: =IF(E40<>0,(E40-F40-G40-H40)/E40,0) -> 0.17424067 | M40: =IF(E40<>0,K40/E40,0) -> -0.55412266 | N40: =IF(COUNTIFS(BD_LUCRO[Mês],$B40)=0,"N/A",IF(K40>=0,"✅ POSITIVO","❌ NEGATIVO")) -> ❌ NEGATIVO | O40: =IF(K39<>0,(K40-K39)/ABS(K39),0) -> -3.8934399
B41: Dezembro/2025 | C41: =COUNTIFS(BD_LUCRO[Mês],$B41) -> 4 | D41: =SUMIFS(BD_LUCRO[Peso Kg],BD_LUCRO[Mês],$B41) -> 761240 | E41: =SUMIFS(BD_LUCRO[Lucro Bruto],BD_LUCRO[Mês],$B41) -> 315994.2 | F41: =SUMIFS(BD_LUCRO[Total Frete],BD_LUCRO[Mês],$B41) -> 206315.9 | G41: =SUMIFS(BD_LUCRO[Impostos],BD_LUCRO[Mês],$B41) -> 14669.32 | H41: =SUMIFS(BD_LUCRO[Comissão],BD_LUCRO[Mês],$B41) -> 3521 | I41: =SUMIFS(BD_LUCRO[Lucro Líq.],BD_LUCRO[Mês],$B41) -> 84051.78 | J41: =SUMIFS(BD_DESP[Valor],BD_DESP[Mês],$B41) -> 305624.58 | K41: =I41-J41 -> -221572.8 | L41: =IF(E41<>0,(E41-F41-G41-H41)/E41,0) -> 0.28952424 | M41: =IF(E41<>0,K41/E41,0) -> -0.70119262 | N41: =IF(COUNTIFS(BD_LUCRO[Mês],$B41)=0,"N/A",IF(K41>=0,"✅ POSITIVO","❌ NEGATIVO")) -> ❌ NEGATIVO | O41: =IF(K40<>0,(K41-K40)/ABS(K40),0) -> -0.38818672
B42: TOTAL ANUAL 2025 | C42: =SUM(C30:C41) -> 124 | D42: =SUM(D30:D41) -> 25716499 | E42: =SUM(E30:E41) -> 6965952.7 | F42: =SUM(F30:F41) -> 3259171.8 | G42: =SUM(G30:G41) -> 7281.97 | H42: =SUM(H30:H41) -> 1826139.8 | I42: =SUM(I30:I41) -> 4200075.4 | J42: =SUM(J30:J41) -> 3677506.7 | K42: =SUM(K30:K41) -> 522568.7 | L42: =IF(E42<>0,(E42-F42-G42-H42)/E42,0) -> 0.26893078 | M42: =IF(E42<>0,K42/E42,0) -> 0.07501755 | N42: =IF(K42>=0,"✅ POSITIVO","❌ NEGATIVO") -> ✅ POSITIVO | O42: -
